[{"nr":1,"move":38,"mina":false},{"nr":2,"move":0,"mina":false},{"nr":3,"move":0,"mina":false},{"nr":4,"move":14,"mina":false},{"nr":5,"move":0,"mina":false},{"nr":6,"move":0,"mina":false},{"nr":7,"move":0,"mina":false},{"nr":8,"move":30,"mina":false},{"nr":9,"move":0,"mina":false},{"nr":10,"move":0,"mina":false},{"nr":11,"move":0,"mina":false},{"nr":12,"move":0,"mina":false},{"nr":13,"move":0,"mina":false},{"nr":14,"move":0,"mina":false},{"nr":15,"move":0,"mina":false},{"nr":16,"move":0,"mina":false},{"nr":17,"move":0,"mina":false},{"nr":18,"move":0,"mina":false},{"nr":19,"move":0,"mina":false},{"nr":20,"move":0,"mina":false},{"nr":21,"move":42,"mina":false},{"nr":22,"move":0,"mina":false},{"nr":23,"move":0,"mina":false},{"nr":24,"move":0,"mina":false},{"nr":25,"move":0,"mina":false},{"nr":26,"move":0,"mina":false},{"nr":27,"move":0,"mina":false},{"nr":28,"move":76,"mina":false},{"nr":29,"move":0,"mina":false},{"nr":30,"move":0,"mina":false},{"nr":31,"move":0,"mina":false},{"nr":32,"move":10,"mina":false},{"nr":33,"move":0,"mina":false},{"nr":34,"move":0,"mina":false},{"nr":35,"move":0,"mina":false},{"nr":36,"move":6,"mina":false},{"nr":37,"move":0,"mina":false},{"nr":38,"move":0,"mina":false},{"nr":39,"move":0,"mina":false},{"nr":40,"move":0,"mina":false},{"nr":41,"move":0,"mina":false},{"nr":42,"move":0,"mina":false},{"nr":43,"move":0,"mina":false},{"nr":44,"move":0,"mina":false},{"nr":45,"move":0,"mina":false},{"nr":46,"move":0,"mina":false},{"nr":47,"move":0,"mina":false},{"nr":48,"move":26,"mina":false},{"nr":49,"move":0,"mina":false},{"nr":50,"move":67,"mina":false},{"nr":51,"move":0,"mina":false},{"nr":52,"move":0,"mina":false},{"nr":53,"move":0,"mina":false},{"nr":54,"move":0,"mina":false},{"nr":55,"move":0,"mina":false},{"nr":56,"move":0,"mina":false},{"nr":57,"move":0,"mina":false},{"nr":58,"move":0,"mina":false},{"nr":59,"move":0,"mina":false},{"nr":60,"move":0,"mina":false},{"nr":61,"move":0,"mina":false},{"nr":62,"move":18,"mina":false},{"nr":63,"move":0,"mina":false},{"nr":64,"move":0,"mina":false},{"nr":65,"move":0,"mina":false},{"nr":66,"move":0,"mina":false},{"nr":67,"move":0,"mina":false},{"nr":68,"move":0,"mina":false},{"nr":69,"move":0,"mina":false},{"nr":70,"move":0,"mina":false},{"nr":71,"move":92,"mina":false},{"nr":72,"move":0,"mina":false},{"nr":73,"move":0,"mina":false},{"nr":74,"move":0,"mina":false},{"nr":75,"move":0,"mina":false},{"nr":76,"move":0,"mina":false},{"nr":77,"move":0,"mina":false},{"nr":78,"move":0,"mina":false},{"nr":79,"move":0,"mina":false},{"nr":80,"move":99,"mina":false},{"nr":81,"move":0,"mina":false},{"nr":82,"move":0,"mina":false},{"nr":83,"move":0,"mina":false},{"nr":84,"move":0,"mina":false},{"nr":85,"move":0,"mina":false},{"nr":86,"move":0,"mina":false},{"nr":87,"move":0,"mina":false},{"nr":88,"move":24,"mina":false},{"nr":89,"move":0,"mina":false},{"nr":90,"move":0,"mina":false},{"nr":91,"move":0,"mina":false},{"nr":92,"move":0,"mina":false},{"nr":93,"move":0,"mina":false},{"nr":94,"move":0,"mina":false},{"nr":95,"move":56,"mina":false},{"nr":96,"move":0,"mina":false},{"nr":97,"move":78,"mina":false},{"nr":98,"move":0,"mina":false},{"nr":99,"move":0,"mina":true},{"nr":100,"move":0,"mina":false}]